pecg/Example.py
pecg/MANIFEST.in
pecg/Preprocessing.py
pecg/_ErrorHandler.py
pecg/_init_.py
pecg/_version.py
pecg/main.py
pecg/pyproject.toml
pecg/setup.cfg
pecg/setup.py
pecg/tox.ini
pecg/ecg/Biomarkers.py
pecg/ecg/FiducialPoints.py
pecg/ecg/IntervalsDuration.py
pecg/ecg/Statistics.py
pecg/ecg/WavesCharacteristics.py
pecg/ecg/__init__.py
pecg/ecg/c_files/00README
pecg/ecg/c_files/A00001_ecg_epltd.dat
pecg/ecg/c_files/A00001_ecg_epltd.epltd0
pecg/ecg/c_files/A00001_ecg_epltd.hea
pecg/ecg/c_files/EpltdAll.py
pecg/ecg/c_files/Makefile
pecg/ecg/c_files/Makefile_bak
pecg/ecg/c_files/_init_.py
pecg/ecg/c_files/analbeat.c
pecg/ecg/c_files/analbeat.h
pecg/ecg/c_files/analbeat.o
pecg/ecg/c_files/bdac.c
pecg/ecg/c_files/bdac.h
pecg/ecg/c_files/bdac.h.gch
pecg/ecg/c_files/bdac.o
pecg/ecg/c_files/bxbep
pecg/ecg/c_files/bxbep.c
pecg/ecg/c_files/classify.c
pecg/ecg/c_files/classify.o
pecg/ecg/c_files/easytest.c
pecg/ecg/c_files/easytest2
pecg/ecg/c_files/easytest_mimic2.c
pecg/ecg/c_files/epltd_all
pecg/ecg/c_files/epltd_all.c
pecg/ecg/c_files/epltd_all.o
pecg/ecg/c_files/epltd_all_oldjuly31_2013.c
pecg/ecg/c_files/epltd_ecgall_mimic2.c
pecg/ecg/c_files/epltd_wqrs_sqi_10s.c
pecg/ecg/c_files/epltd_wqrs_sqi_beatbybeat.c
pecg/ecg/c_files/hrvscript
pecg/ecg/c_files/index.html
pecg/ecg/c_files/inputs.h
pecg/ecg/c_files/match.c
pecg/ecg/c_files/match.h
pecg/ecg/c_files/match.o
pecg/ecg/c_files/mykurtosis.c
pecg/ecg/c_files/noisechk.c
pecg/ecg/c_files/noisechk.o
pecg/ecg/c_files/peak_det
pecg/ecg/c_files/peak_det.exe
pecg/ecg/c_files/peaks.txt
pecg/ecg/c_files/postclas.c
pecg/ecg/c_files/postclas.h
pecg/ecg/c_files/postclas.o
pecg/ecg/c_files/qrsdet.c
pecg/ecg/c_files/qrsdet.h
pecg/ecg/c_files/qrsdet.o
pecg/ecg/c_files/qrsdet2.c
pecg/ecg/c_files/qrsdet2.o
pecg/ecg/c_files/qrsfilt.c
pecg/ecg/c_files/qrsfilt.o
pecg/ecg/c_files/run_peak_det.sh
pecg/ecg/c_files/rythmchk.c
pecg/ecg/c_files/rythmchk.h
pecg/ecg/c_files/rythmchk.o
pecg/ecg/c_files/signal.txt
pecg-2.0.5.dist-info/AUTHORS.rst
pecg-2.0.5.dist-info/LICENSE.txt
pecg-2.0.5.dist-info/METADATA
pecg-2.0.5.dist-info/WHEEL
pecg-2.0.5.dist-info/top_level.txt
pecg-2.0.5.dist-info/RECORD
